{
  "payer": "Cigna",
  "payer_key": "cigna",
  "executive_summary": "Here is a 5-7 sentence executive summary for the reconciled Cigna prior authorization route data:\n\nThe preferred submission method for Cigna prior authorizations is through their provider portal at www.cignaforhcp.com. As a fallback, faxes can be sent to (800) 768-4700, but the deprecated number (800) 768-4695 must not be used. Standard turnaround time is 10-12 days due to a system migration, while urgent requests are processed within 24 hours. Required documents include the PA request form (CG-PA-002), chart notes, step therapy/prior treatment failure documentation, and optional biosimilar consideration. For the focus drug Entyvio, prior anti-TNF failure or contraindication is required, along with the standard documentation. Critically, Cigna is currently undergoing a system migration, which is expected to cause processing delays and potential portal issues. The data analysis revealed 5 conflicting fields, so some information may be uncertain.",
  "summary": {
    "total_fields_discovered": 27,
    "total_fields_output": 10,
    "conflicts_detected": 5,
    "focus_drug": "Entyvio",
    "focus_drug_selection": "Data-driven (high-signal): Entyvio (2 mentions in phone/denial) [Entyvio: 2]",
    "fields_validated_against_raw": 9,
    "json_raw_conflicts": 1
  },
  "payer_warnings": [
    "SYSTEM MIGRATION IN PROGRESS (source: CGN-SRC-002). Expect processing delays and potential portal issues."
  ],
  "best_route": {
    "submission": {
      "preferred_method": "portal",
      "fallback_method": "fax",
      "preferred_url": "www.cignaforhcp.com",
      "portal_notes": [
        "Portal is glitchy during system migration \u2014 fax as backup",
        "System migration notice on page"
      ],
      "fallback_fax": "(800) 768-4700",
      "do_not_use": [
        "(800) 768-4695"
      ],
      "fax_notes": [
        "4700 is new dedicated infusion line since Jan 2026. 4695 still works but goes to general queue (slower)."
      ]
    },
    "required_documents": [
      "PA request form (retrieve from www.cignaforhcp.com; best-known version: CG-PA-002)",
      "Chart notes within 90 days",
      "Step therapy / prior treatment failure documentation",
      "Biosimilar consideration documentation (preferred but not required)"
    ],
    "turnaround": {
      "standard": "10-12 days (system migration delays)",
      "urgent": "24 hours"
    },
    "contact": {
      "general_phone": "(800) 768-4688",
      "appeal_fax": "(800) 768-4699",
      "appeal_phone": "(800) 768-4688, Option 4"
    },
    "all_drug_requirements": {
      "Entyvio": {
        "drug_name": "Entyvio",
        "auth_period_months": 6,
        "prior_treatment_failure_required": true,
        "diagnosis_restrictions": [
          "Crohn's or UC only"
        ],
        "notes": [
          "Anti-TNF failure or contraindication required"
        ]
      },
      "Keytruda": {
        "drug_name": "Keytruda",
        "auth_period_months": 3,
        "turnaround_standard_days": 5
      },
      "Remicade": {
        "drug_name": "Remicade",
        "step_therapy_required": true,
        "auth_period_months": 6,
        "auth_period_renewal_months": 12,
        "auth_period_initial_months": 6,
        "biosimilar_preferred": true,
        "notes": [
          "Biosimilar preferred for new starts (2025)"
        ]
      },
      "Tysabri": {
        "drug_name": "Tysabri",
        "auth_period_months": 12,
        "specific_testing": [
          "JCV antibody"
        ],
        "documentation_requirements": [
          "TOUCH Prescribing Program enrollment verification"
        ],
        "notes": [
          "JCV antibody testing + TOUCH enrollment required"
        ]
      }
    },
    "restrictions": [
      "SYSTEM MIGRATION IN PROGRESS (source: CGN-SRC-002). Expect processing delays and potential portal issues.",
      "Entyvio: Anti-TNF failure or contraindication required",
      "Remicade: Step therapy / prior treatment failure required",
      "Tysabri: JCV antibody testing + TOUCH enrollment required"
    ],
    "data_coverage": {
      "fields_extracted": 27,
      "sources_used": [
        "CGN-SRC-001",
        "CGN-SRC-002",
        "CGN-SRC-003",
        "CGN-SRC-004"
      ],
      "potentially_missing": [
        "Letter Of Medical Necessity",
        "Prescription Order",
        "Diagnosis Codes",
        "Prior Treatment History",
        "Specialist Attestation",
        "Clinical Rationale"
      ],
      "extraction_note": "Based on 4 sources. Cross-validated 9 fields against raw text (1 discrepancies found). Verify with payer if additional documentation needed: Letter Of Medical Necessity, Prescription Order, Diagnosis Codes..."
    }
  },
  "payer_context": {
    "system_migration_in_progress": {
      "value": true,
      "source_id": "CGN-SRC-002",
      "source_date": "2026-03-24"
    }
  },
  "fields": {
    "turnaround": {
      "value": {
        "stated_policy": {
          "urgent": 24,
          "standard": 7
        },
        "operational_reality": {
          "standard": {
            "min": 10,
            "max": 12
          },
          "standard_cause": "system migration delays"
        }
      },
      "confidence": 0.886,
      "source_id": "CGN-SRC-002, CGN-SRC-001",
      "source_type": "composite",
      "source_date": "2026-03-24",
      "decision_path": [
        "field: turnaround",
        "qualifier_only_family: no base field, 2 qualifiers",
        "urgent stated_policy: 24 (conf: 0.92)",
        "standard stated_policy: 7 (conf: 0.85)",
        "standard operational_reality: 10-12 (system migration delays) (conf: 0.88)",
        "overall_confidence: avg of 3 components -> 0.886 (range: 0.85-0.92)",
        "output: {'stated_policy': {'urgent': 24, 'standard': 7}, 'operational_reality': {'standard': {'min': 10, 'max': 12}, 'standard_cause': 'system migration delays'}}"
      ],
      "has_conflicts": true,
      "all_values": {
        "turnaround_urgent": 24,
        "turnaround_standard": 7
      },
      "superseded_values": [],
      "supersession_reasons": [],
      "notes": [],
      "operational_reality": null
    },
    "pa_form": {
      "value": "CG-PA-002",
      "confidence": 0.9,
      "source_id": "CGN-SRC-002",
      "source_type": "phone_transcript",
      "source_date": "2026-03-24",
      "decision_path": [
        "field: pa_form",
        "sources: 4",
        "Value 'CG-PA-001' deprecated by *_old field in CGN-SRC-002",
        "Value matches deprecated *_old value",
        "Value matches deprecated *_old value",
        "freshness: 2026-03-24 (22d old) -> 0.919",
        "authority: phone_transcript -> 0.750",
        "corroboration: 2/2 agree -> 0.500",
        "confidence_floor: 2/2 universal agreement -> 0.850",
        "total: 0.850",
        "selected: CG-PA-002 from CGN-SRC-002",
        "raw_text_validation: Validated against raw text (adjustment: +0.05)"
      ],
      "has_conflicts": true,
      "all_values": {
        "CGN-SRC-001": "CG-PA-001",
        "CGN-SRC-002": "CG-PA-002",
        "CGN-SRC-003": "CG-PA-001",
        "CGN-SRC-004": "CG-PA-002"
      },
      "superseded_values": [
        "CGN-SRC-001",
        "CGN-SRC-003"
      ],
      "supersession_reasons": [
        "Value 'CG-PA-001' deprecated by *_old field in CGN-SRC-002",
        "Value matches deprecated *_old value",
        "Value matches deprecated *_old value"
      ],
      "notes": [
        "CG-PA-001 no longer accepted for infusion drugs as of Jan 2026"
      ],
      "operational_reality": null
    },
    "portal_url": {
      "value": "www.cignaforhcp.com",
      "confidence": 0.95,
      "source_id": "CGN-SRC-001",
      "source_type": "provider_manual",
      "source_date": "2024-06-01",
      "decision_path": [
        "field: portal_url",
        "sources: 3",
        "freshness: 2024-06-01 (683d old) -> 0.072",
        "authority: provider_manual -> 0.500",
        "corroboration: 3/3 agree -> 0.750",
        "confidence_floor: 3/3 universal agreement -> 0.925",
        "total: 0.925",
        "selected: www.cignaforhcp.com from CGN-SRC-001",
        "raw_text_validation: Validated against raw text (adjustment: +0.05)"
      ],
      "has_conflicts": false,
      "all_values": {
        "CGN-SRC-001": "www.cignaforhcp.com",
        "CGN-SRC-002": "www.cignaforhcp.com",
        "CGN-SRC-003": "www.cignaforhcp.com"
      },
      "superseded_values": [],
      "supersession_reasons": [],
      "notes": [
        "Portal is glitchy during system migration \u2014 fax as backup",
        "System migration notice on page"
      ],
      "operational_reality": null
    },
    "chart_note_window_days": {
      "value": 90,
      "confidence": 0.911,
      "source_id": "CGN-SRC-004",
      "source_type": "denial_letter",
      "source_date": "2026-03-15",
      "decision_path": [
        "field: chart_note_window_days",
        "sources: 4",
        "Source CGN-SRC-001 (2024-06-01) predates policy update (2026-01-01)",
        "Source CGN-SRC-003 (2025-08-01) predates policy update (2026-01-01)",
        "Policy update (2026-01-01) found in source CGN-SRC-004",
        "freshness: 2026-03-15 (31d old) -> 0.887",
        "authority: denial_letter -> 1.000",
        "corroboration: 2/2 agree -> 0.500",
        "policy_boost: source has policy_update -> +1.000",
        "total: 0.861",
        "selected: 90 from CGN-SRC-004",
        "raw_text_validation: Validated against raw text (adjustment: +0.05)"
      ],
      "has_conflicts": true,
      "all_values": {
        "CGN-SRC-001": 60,
        "CGN-SRC-002": 90,
        "CGN-SRC-003": 60,
        "CGN-SRC-004": 90
      },
      "superseded_values": [
        "CGN-SRC-001",
        "CGN-SRC-003"
      ],
      "supersession_reasons": [
        "Source CGN-SRC-001 (2024-06-01) predates policy update (2026-01-01)",
        "Source CGN-SRC-003 (2025-08-01) predates policy update (2026-01-01)",
        "Policy update (2026-01-01) found in source CGN-SRC-004"
      ],
      "notes": [],
      "operational_reality": null
    },
    "fax_number": {
      "value": "(800) 768-4700",
      "confidence": 0.9,
      "source_id": "CGN-SRC-002",
      "source_type": "phone_transcript",
      "source_date": "2026-03-24",
      "decision_path": [
        "field: fax_number",
        "sources: 4",
        "Value '(800) 768-4695' deprecated by *_old field in CGN-SRC-002",
        "Value '(800) 768-4695' deprecated by *_old field in CGN-SRC-004",
        "Value matches deprecated *_old value",
        "Value matches deprecated *_old value",
        "freshness: 2026-03-24 (22d old) -> 0.919",
        "authority: phone_transcript -> 0.750",
        "corroboration: 2/2 agree -> 0.500",
        "confidence_floor: 2/2 universal agreement -> 0.850",
        "total: 0.850",
        "selected: (800) 768-4700 from CGN-SRC-002",
        "raw_text_validation: Validated against raw text (adjustment: +0.05)"
      ],
      "has_conflicts": true,
      "all_values": {
        "CGN-SRC-001": "(800) 768-4695",
        "CGN-SRC-002": "(800) 768-4700",
        "CGN-SRC-003": "(800) 768-4695",
        "CGN-SRC-004": "(800) 768-4700"
      },
      "superseded_values": [
        "CGN-SRC-001",
        "CGN-SRC-003"
      ],
      "supersession_reasons": [
        "Value '(800) 768-4695' deprecated by *_old field in CGN-SRC-002",
        "Value '(800) 768-4695' deprecated by *_old field in CGN-SRC-004",
        "Value matches deprecated *_old value",
        "Value matches deprecated *_old value"
      ],
      "notes": [
        "4700 is new dedicated infusion line since Jan 2026. 4695 still works but goes to general queue (slower)."
      ],
      "operational_reality": null
    },
    "appeal_phone": {
      "value": "(800) 768-4688, Option 4",
      "confidence": 0.75,
      "source_id": "CGN-SRC-004",
      "source_type": "denial_letter",
      "source_date": "2026-03-15",
      "decision_path": [
        "field: appeal_phone",
        "sources: 1",
        "freshness: 2026-03-15 (31d old) -> 0.887",
        "authority: denial_letter -> 1.000",
        "corroboration: 1/1 agree -> 0.000",
        "confidence_floor: single-source denial_letter (official policy) -> 0.700",
        "total: 0.700",
        "selected: (800) 768-4688, Option 4 from CGN-SRC-004",
        "raw_text_validation: Validated against raw text (adjustment: +0.05)"
      ],
      "has_conflicts": false,
      "all_values": {
        "CGN-SRC-004": "(800) 768-4688, Option 4"
      },
      "superseded_values": [],
      "supersession_reasons": [],
      "notes": [],
      "operational_reality": null
    },
    "appeal_fax": {
      "value": "(800) 768-4699",
      "confidence": 0.75,
      "source_id": "CGN-SRC-004",
      "source_type": "denial_letter",
      "source_date": "2026-03-15",
      "decision_path": [
        "field: appeal_fax",
        "sources: 1",
        "freshness: 2026-03-15 (31d old) -> 0.887",
        "authority: denial_letter -> 1.000",
        "corroboration: 1/1 agree -> 0.000",
        "confidence_floor: single-source denial_letter (official policy) -> 0.700",
        "total: 0.700",
        "selected: (800) 768-4699 from CGN-SRC-004",
        "raw_text_validation: Validated against raw text (adjustment: +0.05)"
      ],
      "has_conflicts": false,
      "all_values": {
        "CGN-SRC-004": "(800) 768-4699"
      },
      "superseded_values": [],
      "supersession_reasons": [],
      "notes": [],
      "operational_reality": null
    },
    "phone": {
      "value": "(800) 768-4688",
      "confidence": 0.9,
      "source_id": "CGN-SRC-001",
      "source_type": "provider_manual",
      "source_date": "2024-06-01",
      "decision_path": [
        "field: phone",
        "sources: 2",
        "freshness: 2024-06-01 (683d old) -> 0.072",
        "authority: provider_manual -> 0.500",
        "corroboration: 2/2 agree -> 0.500",
        "confidence_floor: 2/2 universal agreement -> 0.850",
        "total: 0.850",
        "selected: (800) 768-4688 from CGN-SRC-001",
        "raw_text_validation: Validated against raw text (adjustment: +0.05)"
      ],
      "has_conflicts": false,
      "all_values": {
        "CGN-SRC-001": "(800) 768-4688",
        "CGN-SRC-003": "(800) 768-4688"
      },
      "superseded_values": [],
      "supersession_reasons": [],
      "notes": [],
      "operational_reality": null
    },
    "phone_hours": {
      "value": "M-F 8am-8pm EST, Sat 9am-1pm EST",
      "confidence": 0.65,
      "source_id": "CGN-SRC-001",
      "source_type": "provider_manual",
      "source_date": "2024-06-01",
      "decision_path": [
        "field: phone_hours",
        "sources: 1",
        "freshness: 2024-06-01 (683d old) -> 0.072",
        "authority: provider_manual -> 0.500",
        "corroboration: 1/1 agree -> 0.000",
        "confidence_floor: single-source provider_manual (official policy) -> 0.700",
        "total: 0.700",
        "selected: M-F 8am-8pm EST, Sat 9am-1pm EST from CGN-SRC-001",
        "raw_text_validation: Day value M-F 8am-8pm EST, Sat 9am-1pm EST not confirmed in raw text (adjustment: -0.05)"
      ],
      "has_conflicts": false,
      "all_values": {
        "CGN-SRC-001": "M-F 8am-8pm EST, Sat 9am-1pm EST"
      },
      "superseded_values": [],
      "supersession_reasons": [],
      "notes": [],
      "operational_reality": null
    },
    "submission_methods": {
      "value": [
        "portal",
        "fax"
      ],
      "confidence": 0.584,
      "source_id": "CGN-SRC-002",
      "source_type": "phone_transcript",
      "source_date": "2026-03-24",
      "decision_path": [
        "field: submission_methods",
        "sources: 3",
        "freshness: 2026-03-24 (22d old) -> 0.919",
        "authority: phone_transcript -> 0.750",
        "corroboration: 1/3 agree -> 0.000",
        "total: 0.584",
        "selected: ['portal', 'fax'] from CGN-SRC-002"
      ],
      "has_conflicts": true,
      "all_values": {
        "CGN-SRC-001": [
          "portal",
          "fax",
          "phone_urgent_only"
        ],
        "CGN-SRC-002": [
          "portal",
          "fax"
        ],
        "CGN-SRC-003": [
          "portal",
          "fax",
          "phone"
        ]
      },
      "superseded_values": [],
      "supersession_reasons": [],
      "notes": [],
      "operational_reality": null
    }
  },
  "all_drugs": {
    "Entyvio": {
      "drug_name": "Entyvio",
      "fields": {
        "auth_period_months": 6,
        "prior_treatment_failure_required": true,
        "diagnosis_restrictions": [
          "Crohn's or UC only"
        ]
      },
      "sources": [
        "CGN-SRC-001"
      ],
      "notes": [
        "Anti-TNF failure or contraindication required"
      ]
    },
    "Keytruda": {
      "drug_name": "Keytruda",
      "fields": {
        "auth_period_months": 3,
        "turnaround_standard_days": 5
      },
      "sources": [
        "CGN-SRC-001"
      ],
      "notes": []
    },
    "Remicade": {
      "drug_name": "Remicade",
      "fields": {
        "step_therapy_required": true,
        "auth_period_months": 6,
        "auth_period_renewal_months": 12,
        "auth_period_initial_months": 6,
        "biosimilar_preferred": true
      },
      "sources": [
        "CGN-SRC-001"
      ],
      "notes": [
        "Biosimilar preferred for new starts (2025)"
      ]
    },
    "Tysabri": {
      "drug_name": "Tysabri",
      "fields": {
        "auth_period_months": 12,
        "specific_testing": [
          "JCV antibody"
        ],
        "documentation_requirements": [
          "TOUCH Prescribing Program enrollment verification"
        ]
      },
      "sources": [
        "CGN-SRC-001"
      ],
      "notes": [
        "JCV antibody testing + TOUCH enrollment required"
      ]
    }
  },
  "raw_text_validations": {
    "pa_form": {
      "field_name": "pa_form",
      "json_value": "CG-PA-002",
      "found_in_raw": true,
      "raw_matches": [
        "CG-PA-002"
      ],
      "confidence_adjustment": 0.05,
      "note": "Validated against raw text"
    },
    "portal_url": {
      "field_name": "portal_url",
      "json_value": "www.cignaforhcp.com",
      "found_in_raw": true,
      "raw_matches": [
        "www.cignaforhcp.com"
      ],
      "confidence_adjustment": 0.05,
      "note": "Validated against raw text"
    },
    "chart_note_window_days": {
      "field_name": "chart_note_window_days",
      "json_value": "90",
      "found_in_raw": true,
      "raw_matches": [
        "90"
      ],
      "confidence_adjustment": 0.05,
      "note": "Validated against raw text"
    },
    "fax_number": {
      "field_name": "fax_number",
      "json_value": "(800) 768-4700",
      "found_in_raw": true,
      "raw_matches": [
        "(800) 768-4700"
      ],
      "confidence_adjustment": 0.05,
      "note": "Validated against raw text"
    },
    "appeal_phone": {
      "field_name": "appeal_phone",
      "json_value": "(800) 768-4688, Option 4",
      "found_in_raw": true,
      "raw_matches": [
        "(800) 768-4688"
      ],
      "confidence_adjustment": 0.05,
      "note": "Validated against raw text"
    },
    "appeal_fax": {
      "field_name": "appeal_fax",
      "json_value": "(800) 768-4699",
      "found_in_raw": true,
      "raw_matches": [
        "(800) 768-4699"
      ],
      "confidence_adjustment": 0.05,
      "note": "Validated against raw text"
    },
    "phone": {
      "field_name": "phone",
      "json_value": "(800) 768-4688",
      "found_in_raw": true,
      "raw_matches": [
        "(800) 768-4688"
      ],
      "confidence_adjustment": 0.05,
      "note": "Validated against raw text"
    },
    "phone_hours": {
      "field_name": "phone_hours",
      "json_value": "M-F 8am-8pm EST, Sat 9am-1pm EST",
      "found_in_raw": false,
      "raw_matches": [],
      "confidence_adjustment": -0.05,
      "note": "Day value M-F 8am-8pm EST, Sat 9am-1pm EST not confirmed in raw text"
    },
    "submission_methods": {
      "field_name": "submission_methods",
      "json_value": "['portal', 'fax']",
      "found_in_raw": false,
      "raw_matches": [],
      "confidence_adjustment": 0.0,
      "note": "Skipped validation for complex type (list/dict)"
    }
  },
  "raw_fields": {
    "turnaround": {
      "source_count": 0,
      "values": []
    },
    "pa_form": {
      "source_count": 4,
      "values": [
        {
          "value": "CG-PA-001",
          "source_id": "CGN-SRC-001",
          "source_type": "provider_manual",
          "source_date": "2024-06-01"
        },
        {
          "value": "CG-PA-002",
          "source_id": "CGN-SRC-002",
          "source_type": "phone_transcript",
          "source_date": "2026-03-24"
        },
        {
          "value": "CG-PA-001",
          "source_id": "CGN-SRC-003",
          "source_type": "web_page",
          "source_date": "2025-08-01"
        },
        {
          "value": "CG-PA-002",
          "source_id": "CGN-SRC-004",
          "source_type": "denial_letter",
          "source_date": "2026-03-15"
        }
      ]
    },
    "portal_url": {
      "source_count": 3,
      "values": [
        {
          "value": "www.cignaforhcp.com",
          "source_id": "CGN-SRC-001",
          "source_type": "provider_manual",
          "source_date": "2024-06-01"
        },
        {
          "value": "www.cignaforhcp.com",
          "source_id": "CGN-SRC-002",
          "source_type": "phone_transcript",
          "source_date": "2026-03-24"
        },
        {
          "value": "www.cignaforhcp.com",
          "source_id": "CGN-SRC-003",
          "source_type": "web_page",
          "source_date": "2025-08-01"
        }
      ]
    },
    "chart_note_window_days": {
      "source_count": 4,
      "values": [
        {
          "value": 60,
          "source_id": "CGN-SRC-001",
          "source_type": "provider_manual",
          "source_date": "2024-06-01"
        },
        {
          "value": 90,
          "source_id": "CGN-SRC-002",
          "source_type": "phone_transcript",
          "source_date": "2026-03-24"
        },
        {
          "value": 60,
          "source_id": "CGN-SRC-003",
          "source_type": "web_page",
          "source_date": "2025-08-01"
        },
        {
          "value": 90,
          "source_id": "CGN-SRC-004",
          "source_type": "denial_letter",
          "source_date": "2026-03-15"
        }
      ]
    },
    "fax_number": {
      "source_count": 4,
      "values": [
        {
          "value": "(800) 768-4695",
          "source_id": "CGN-SRC-001",
          "source_type": "provider_manual",
          "source_date": "2024-06-01"
        },
        {
          "value": "(800) 768-4700",
          "source_id": "CGN-SRC-002",
          "source_type": "phone_transcript",
          "source_date": "2026-03-24"
        },
        {
          "value": "(800) 768-4695",
          "source_id": "CGN-SRC-003",
          "source_type": "web_page",
          "source_date": "2025-08-01"
        },
        {
          "value": "(800) 768-4700",
          "source_id": "CGN-SRC-004",
          "source_type": "denial_letter",
          "source_date": "2026-03-15"
        }
      ]
    },
    "appeal_phone": {
      "source_count": 1,
      "values": [
        {
          "value": "(800) 768-4688, Option 4",
          "source_id": "CGN-SRC-004",
          "source_type": "denial_letter",
          "source_date": "2026-03-15"
        }
      ]
    },
    "appeal_fax": {
      "source_count": 1,
      "values": [
        {
          "value": "(800) 768-4699",
          "source_id": "CGN-SRC-004",
          "source_type": "denial_letter",
          "source_date": "2026-03-15"
        }
      ]
    },
    "phone": {
      "source_count": 2,
      "values": [
        {
          "value": "(800) 768-4688",
          "source_id": "CGN-SRC-001",
          "source_type": "provider_manual",
          "source_date": "2024-06-01"
        },
        {
          "value": "(800) 768-4688",
          "source_id": "CGN-SRC-003",
          "source_type": "web_page",
          "source_date": "2025-08-01"
        }
      ]
    },
    "phone_hours": {
      "source_count": 1,
      "values": [
        {
          "value": "M-F 8am-8pm EST, Sat 9am-1pm EST",
          "source_id": "CGN-SRC-001",
          "source_type": "provider_manual",
          "source_date": "2024-06-01"
        }
      ]
    },
    "system_migration_in_progress": {
      "source_count": 1,
      "values": [
        {
          "value": true,
          "source_id": "CGN-SRC-002",
          "source_type": "phone_transcript",
          "source_date": "2026-03-24"
        }
      ]
    },
    "submission_methods": {
      "source_count": 3,
      "values": [
        {
          "value": [
            "portal",
            "fax",
            "phone_urgent_only"
          ],
          "source_id": "CGN-SRC-001",
          "source_type": "provider_manual",
          "source_date": "2024-06-01"
        },
        {
          "value": [
            "portal",
            "fax"
          ],
          "source_id": "CGN-SRC-002",
          "source_type": "phone_transcript",
          "source_date": "2026-03-24"
        },
        {
          "value": [
            "portal",
            "fax",
            "phone"
          ],
          "source_id": "CGN-SRC-003",
          "source_type": "web_page",
          "source_date": "2025-08-01"
        }
      ]
    }
  }
}